MANIFEST.in
README.rst
requirements.txt
setup.cfg
setup.py
celery_cloudwatch/__init__.py
celery_cloudwatch/__main__.py
celery_cloudwatch/monitor.py
celery_cloudwatch_logs.egg-info/PKG-INFO
celery_cloudwatch_logs.egg-info/SOURCES.txt
celery_cloudwatch_logs.egg-info/dependency_links.txt
celery_cloudwatch_logs.egg-info/entry_points.txt
celery_cloudwatch_logs.egg-info/requires.txt
celery_cloudwatch_logs.egg-info/top_level.txt