Metadata-Version: 1.1
Name: celery-cloudwatch-logs
Version: 1.3
Summary: Uploads results of Celery tasks to AWS CloudWatch.
Home-page: https://github.com/SectorLabs/celery-cloudwatch
Author: Sector Labs
Author-email: open-source@sectorlabs.ro
License: MIT License
Keywords: celery,aws,cloudwatch
Platform: UNKNOWN
Classifier: Intended Audience :: Developers
Classifier: License :: OSI Approved :: MIT License
Classifier: Operating System :: OS Independent
Classifier: Programming Language :: Python
Classifier: Programming Language :: Python :: 3.5
